mixfit/__init__.py
mixfit/mixfit.py
mixfitfunctions/__init__.py
mixfitfunctions/cauchy.py
mixfitfunctions/constant.py
mixfitfunctions/differentialcauchy.py
mixfitfunctions/differentialgaussian.py
mixfitfunctions/gaussian.py
mixfitfunctions/linear.py
mixfitfunctions/mixfitfunction.py
pymixfit_tspspi-0.0.1.dist-info/LICENSE.md
pymixfit_tspspi-0.0.1.dist-info/METADATA
pymixfit_tspspi-0.0.1.dist-info/WHEEL
pymixfit_tspspi-0.0.1.dist-info/top_level.txt
pymixfit_tspspi-0.0.1.dist-info/RECORD
