Metadata-Version: 2.1
Name: pymixfit-tspspi
Version: 0.0.1
Summary: Mixture fitting
Home-page: https://github.com/tspspi/pymixfit
Author: Thomas Spielauer
Author-email: pypipackages01@tspi.at
Classifier: Programming Language :: Python :: 3
Classifier: License :: OSI Approved :: BSD License
Classifier: Operating System :: OS Independent
Requires-Python: >=3.6
License-File: LICENSE.md
Requires-Dist: numpy >=1.25
Requires-Dist: lmfit >=1.3.1
